culingam/__init__.py
culingam/base.py
culingam/basic.cu
culingam/basic_wrapper.cpp
culingam/directlingam.py
culingam/utils.py
culingam/varlingam.py
culingam/include/basic.cuh
culingam-0.0.1.dist-info/WHEEL
culingam-0.0.1.dist-info/METADATA
culingam-0.0.1.dist-info/RECORD
