Metadata-Version: 2.1
Name: culingam
Version: 0.0.1
Summary: CULiNGAM accelerates LiNGAM analysis on GPUs.
Author-email: Victor Akinwande <viktour19@gmail.com>
Requires-Python: >=3.8
Classifier: Programming Language :: Python :: 3
Classifier: License :: OSI Approved :: MIT License
Classifier: Operating System :: OS Independent
Requires-Dist: numpy
Requires-Dist: tqdm
Project-URL: Homepage, https://github.com/viktour19/culingam
Project-URL: Issues, https://github.com/viktour19/culingam/issues
